audit_client/__init__.py
audit_client/audit_client.py
audit_client/component_service.py
audit_client/models.py
audit_client/utils.py
tests/__init__.py
tests/test_audit_client.py
dhx_audit_client-1.0.11b42.dist-info/METADATA
dhx_audit_client-1.0.11b42.dist-info/WHEEL
dhx_audit_client-1.0.11b42.dist-info/top_level.txt
dhx_audit_client-1.0.11b42.dist-info/RECORD
