Metadata-Version: 2.1
Name: dhx-audit-client
Version: 1.0.11b42
Summary: General audit client for services using DataHex based solutions.
Home-page: https://github.com/rozettatechnology/datahex-audit
Author: RoZetta Technology
Author-email: developers@rozettatechnology.com
License: UNKNOWN
Platform: UNKNOWN
Classifier: Development Status :: 3 - Alpha
Classifier: Environment :: Console
Classifier: Intended Audience :: Developers
Classifier: License :: Other/Proprietary License
Classifier: Natural Language :: English
Classifier: Operating System :: Unix
Classifier: Programming Language :: Python
Classifier: Topic :: Software Development
Requires-Dist: pip (>=19.1.1)
Requires-Dist: boto3 (~=1.16)
Requires-Dist: botocore (~=1.19)
